{"invno":{"label":"Object number","value":"91.28.27","order":9},"description":{"label":"Description","value":"A tall adjustable standing / floor single candelholder set on a thin stem with three arrow feet.","order":11},"medium":{"label":"Medium","value":"Iron","order":6},"title":{"label":"Title","value":"Adjustable Candleholder","order":2},"classification":{"label":"Classification","value":"Furniture","order":0},"people":{"label":"Artist/Maker/Culture","value":"Unidentified maker","order":2},"primaryMedia":{"label":"","value":"91-28-27_i1r.jpg","order":1},"depth":{"label":"Depth","value":"109.5377000000","order":0},"displayDate":{"label":"Date","value":"18th century","order":3},"locations":{"label":"Location","value":"[{purpose=org.hibernate.tuple.entity.CustomMapTuplizerImpl$CustomMapInstantiator$1@4, sortNumber=    91    28   27                                                               , location=org.hibernate.tuple.entity.CustomMapTuplizerImpl$CustomMapInstantiator$1@33, id={componentID=471, objectID=469, objlocationID=233523}, $type$=ObjectsLocations}]","order":16},"id":{"label":"Id","value":469,"order":0},"dimensions":{"label":"Dimensions","value":"Overall: 43 1/8 x 15 3/4 x 16 in. (109.5 x 40 x 40.6 cm)","order":5},"height":{"label":"Height","value":"40.6401000000","order":0}}